xlfilldown/__init__.py
xlfilldown/api.py
xlfilldown/cli.py
xlfilldown/core.py
xlfilldown-1.0.3.dist-info/licenses/LICENSE
xlfilldown-1.0.3.dist-info/METADATA
xlfilldown-1.0.3.dist-info/WHEEL
xlfilldown-1.0.3.dist-info/entry_points.txt
xlfilldown-1.0.3.dist-info/top_level.txt
xlfilldown-1.0.3.dist-info/RECORD
