Metadata-Version: 2.4
Name: xlfilldown
Version: 1.0.3
Summary: Stream an Excel sheet into SQLite or Excel with forward-fill padding, preserved Excel row numbers, and a stable row hash.
Author-email: Good Boy <pythonic@rexbytes.com>
License: MIT
Project-URL: Homepage, https://github.com/RexBytes/xlfilldown
Project-URL: Documentation, https://rexbytes.com/2025/09/23/xlfilldown-the-complete-guide/
Project-URL: Changelog, https://github.com/RexBytes/xlfilldown/releases
Keywords: excel,sqlite,etl,forward-fill,padding,hash
Classifier: Programming Language :: Python :: 3
Classifier: License :: OSI Approved :: MIT License
Classifier: Operating System :: OS Independent
Classifier: Topic :: Database
Classifier: Topic :: Utilities
Requires-Python: >=3.9
License-File: LICENSE
Requires-Dist: openpyxl>=3.1.0
Dynamic: license-file
